setup.py
src/relatime/__init__.py
src/relatime.egg-info/PKG-INFO
src/relatime.egg-info/SOURCES.txt
src/relatime.egg-info/dependency_links.txt
src/relatime.egg-info/not-zip-safe
src/relatime.egg-info/pbr.json
src/relatime.egg-info/requires.txt
src/relatime.egg-info/top_level.txt