Metadata-Version: 1.1
Name: relatime
Version: 1.1.0
Summary: Python parser for a simple relative time syntax
Home-page: https://github.com/mcm/relatime
Author: Steve McMaster
Author-email: mcmaster@hurricanelabs.com
License: UNKNOWN
Platform: UNKNOWN
Classifier: License :: OSI Approved :: MIT License
Classifier: Programming Language :: Python :: 3 :: Only
Classifier: Development Status :: 4 - Beta
